django_sql_profiler/__init__.py
django_sql_profiler/src/__init__.py
django_sql_profiler-0.0.12.dist-info/METADATA
django_sql_profiler-0.0.12.dist-info/WHEEL
django_sql_profiler-0.0.12.dist-info/top_level.txt
django_sql_profiler-0.0.12.dist-info/RECORD
