Metadata-Version: 2.1
Name: django-sql-profiler
Version: 0.0.12
Summary: Simple SQL Profiler for Django
Author: David (thinhit@yahoo.com)
Classifier: Programming Language :: Python :: 3
Classifier: License :: OSI Approved :: MIT License
Classifier: Operating System :: OS Independent
Requires-Python: >=3.6
Requires-Dist: pymongo
